[
{"guid":"c88fa891abed","title":"Arles Old Town - Arles Vieille Ville. France, Provence","latlng":"43.677768, 4.628860","youtubeId":"CgqgRxfVXLI","publishedAt":"2017-02-22T16:55:05.000Z"},
{"guid":"fed5a494b9b7","title":"Saint-Restitut, France, Provence","latlng":"44.331667, 4.789901","youtubeId":"Ttaw-Dix9DE","publishedAt":"2017-02-08T15:10:50.000Z"},
{"guid":"cb078e44a1f0","title":"Saignon, France, Provence","latlng":"43.862988, 5.428817","youtubeId":"ktwYyVE2qw8","publishedAt":"2017-01-25T15:04:36.000Z"},
{"guid":"4223351f5f84","title":"Barbegal aqueduct and mill, Arles / Fontvieille. France, Provence","latlng":"43.703929, 4.721401","youtubeId":"wqG31mM-Maw","publishedAt":"2017-01-18T15:47:21.000Z"},
{"guid":"31558acdbfa8","title":"Séguret, France, Provence","latlng":"44.205100, 5.023722","youtubeId":"dk0tg-oATX8","publishedAt":"2017-01-04T15:32:35.000Z"},
{"guid":"705f778cc512","title":"Château d'Estoublon apres rénovation - Château d'Estoublon after renovation","latlng":"43.733543, 4.740694","youtubeId":"d8dQhd6SZzI","publishedAt":"2016-12-28T16:38:37.000Z"},
{"guid":"ba9fe0892435","title":"Zamek Ogrodzieniec (The Ogrodzieniec Castle), Polska (Poland)","latlng":"50.453113, 19.552105","youtubeId":"qYOw2SqFmi8","publishedAt":"2016-12-21T17:04:57.000Z"},
{"guid":"4a8c5a1e0166","title":"Starý Smokovec, Slovensko (Slovakia, Słowacja)","latlng":"49.139481, 20.220575","youtubeId":"IH-qNfn3t2o","publishedAt":"2016-12-14T16:39:20.000Z"},
{"guid":"969f32b42ac8","title":"Abbaye Notre-Dame de Sénanque, Gordes, France, Provence","latlng":"43.928259, 5.186655","youtubeId":"iV2-NCBaKK8","publishedAt":"2016-12-07T17:14:44.000Z"},
{"guid":"1fe3d14f92b7","title":"Gordes - a beautiful hilltop village, France, Provence","latlng":"43.911015, 5.200045","youtubeId":"nQ2N4bOLkzE","publishedAt":"2016-11-30T15:24:23.000Z"},
{"guid":"4e37cdff5316","title":"L'Isle-sur-la-Sorgue - the Town of Water, France, Provence","latlng":"43.920115, 5.051776","youtubeId":"plRX12E-YQM","publishedAt":"2016-11-23T14:58:33.000Z"},
{"guid":"f020049b9eaa","title":"Toulovcovy Maštale (Toulovec's Stables), Česko (Czechia)","latlng":"49.820628, 16.140977","youtubeId":"1JanYORoDcE","publishedAt":"2016-11-16T16:41:49.000Z"},
{"guid":"aa503a06c16f","title":"Štramberk in autumn (Podzim ve Štramberku), Czech Republic - Česko","latlng":"49.591406, 18.116690","youtubeId":"_6yoK3Raw94","publishedAt":"2016-11-09T17:21:39.000Z"},
{"guid":"87a86f672d94","title":"Cadenet, France, Provence","latlng":"43.734542, 5.373508","youtubeId":"hBcMrlzYre8","publishedAt":"2016-11-02T17:20:37.000Z"},
{"guid":"2c3e032efdf0","title":"Fontaine-de-Vaucluse - the Village of the Spring, Provence, France","latlng":"43.921816, 5.127952","youtubeId":"nwuwTv4KlCY","publishedAt":"2016-10-26T17:35:31.000Z"},
{"guid":"bdffa36e8189","title":"Roussillon (Old Town - Vieille Ville), France, Provence","latlng":"43.902726, 5.292520","youtubeId":"mEj5ZOwsocs","publishedAt":"2016-10-19T15:24:28.000Z"},
{"guid":"4bd4b0bb2736","title":"Kroměříž - Arcibiskupské zahrady (Archbishop's Gardens), Czech Republic","latlng":"49.300471, 17.393474","youtubeId":"iObg8lbEwpI","publishedAt":"2016-09-28T15:04:13.000Z"},
{"guid":"cdd32d73320a","title":"Avignon Rocher des Doms (The Gardens), France, Provence","latlng":"43.952858, 4.807650","youtubeId":"3cOY7OIXc3E","publishedAt":"2016-10-12T14:27:40.000Z"},
{"guid":"48cd63da97b3","title":"Tarascon - Old Town (Vieille Ville), Provence, France","latlng":"43.806415, 4.655155","youtubeId":"0hM8J4hyAaM","publishedAt":"2016-09-22T18:20:04.000Z"},
{"guid":"3c62e7d8bf6c","title":"Nyons, France, Provence","latlng":"44.360206, 5.139775","youtubeId":"XELhrmbbcUE","publishedAt":"2016-09-14T17:24:46.000Z"},
{"guid":"0830d94a9c0c","title":"Cannes, France - Film Festival Palace","latlng":"43.550645, 7.017527","youtubeId":"STWw_xGIBQg","publishedAt":"2016-09-07T14:23:44.000Z"},
{"guid":"90efcba0669f","title":"Paczków (Patschkau), Polska Poland","latlng":"50.462587, 17.007702","youtubeId":"hZPEemLjxAU","publishedAt":"2016-09-07T14:23:57.000Z"},
{"guid":"ca57d79dcb20","title":"HD & 4K Travel Channel Promo Video","latlng":"","youtubeId":"--sogbZ5o30","publishedAt":"2016-09-07T14:23:31.000Z"},
{"guid":"4311af307913","title":"Les Baux-de-Provence - the Castle (Château des Baux), Provence, France","latlng":"43.743789, 4.795153","youtubeId":"PeJylAOYPTc","publishedAt":"2016-08-24T17:54:34.000Z"},
{"guid":"685c20d70318","title":"Hrad Helfštýn (Zamek Helfštýn, Helfštýn Castle), Česko - Czech Republic","latlng":"49.517448, 17.627526","youtubeId":"O8-UVniUP48","publishedAt":"2016-08-14T14:39:54.000Z"},
{"guid":"ed5953173f2e","title":"Les Baux-de-Provence - Old Town (Vieille Ville), Provence, France","latlng":"43.743024, 4.794328","youtubeId":"6oOk0GC5jfM","publishedAt":"2016-08-17T19:08:46.000Z"},
{"guid":"d0a076210193","title":"Visiting Saint-Rémy-de-Provence in Provence, France","latlng":"43.788685, 4.831366","youtubeId":"PqYPA5fCaUE","publishedAt":"2016-08-10T13:52:53.000Z"},
{"guid":"ffaa577a38c2","title":"Arles - Thermes de Constantin (Constantine Baths), Provence, France","latlng":"43.678856, 4.627010","youtubeId":"s8xxDGA4DLg","publishedAt":"2016-08-31T13:47:01.000Z"},
{"guid":"876d0e73ccac","title":"Vaison-la-Romaine - Roman ruins, Provence, France","latlng":"44.243775, 5.075427","youtubeId":"VpCszbzVGwQ","publishedAt":"2016-08-03T13:31:01.000Z"},
{"guid":"fde1d4fcb220","title":"Vaison-la-Romaine, Provence, France","latlng":"44.238933, 5.074573","youtubeId":"9l-flNTpNqI","publishedAt":"2016-07-27T14:20:50.000Z"},
{"guid":"84581ed18837","title":"Ribeauvillé, Alsace (Elsass), France","latlng":"48.194895, 7.319135","youtubeId":"Pue1DRLF0HQ","publishedAt":"2016-07-20T14:25:34.000Z"},
{"guid":"9a1c0581cdd4","title":"Aigues-Mortes, Southern France","latlng":"43.566617, 4.190636","youtubeId":"n9CLlc8I_a4","publishedAt":"2016-07-06T14:47:46.000Z"},
{"guid":"6a9b693a3040","title":"One Day in Nîmes, Southern France","latlng":"43.836905, 4.359160","youtubeId":"AHcfQHmIR6c","publishedAt":"2016-06-30T09:16:13.000Z"},
{"guid":"587380b083f5","title":"Kraków Zamek Królewski na Wawelu (Wawel Royal Castle), Polska (Poland)","latlng":"50.054036, 19.935434","youtubeId":"Zc1vrfTpB9A","publishedAt":"2016-07-13T14:05:31.000Z"},
{"guid":"d4add4a32a8c","title":"Radun Castle near Opava (Zámek Raduň), Czechia - Czech Republic (Česko)","latlng":"49.891267, 17.944559","youtubeId":"xhiSwCDw80k","publishedAt":"2016-05-25T15:27:10.000Z"},
{"guid":"caa80fe463b9","title":"Rudy Wielkie: opactwo cystersów i park (Cistercian abbey & the park), Polska ","latlng":"50.194442, 18.448430","youtubeId":"wCUKjUkBBcw","publishedAt":"2016-05-18T16:16:26.000Z"},
{"guid":"73dd52652546","title":"Le Barroux - castle & abbey (château et abbaye Sainte-Madeleine du Barroux), Provence","latlng":"44.152675, 5.098380","youtubeId":"xGvcQhgZUfc","publishedAt":"2016-05-11T17:34:29.000Z"},
{"guid":"3ebf3a53d2ed","title":"A day in Saintes-Maries-de-la-Mer, France, Provence","latlng":"43.451434, 4.427411","youtubeId":"7RO6HvM36y0","publishedAt":"2016-05-04T14:19:22.000Z"},
{"guid":"7fe1b2b56af4","title":"Pont du Gard - ancient Roman aqueduct, Provence, France","latlng":"43.947543, 4.535014","youtubeId":"yks6Y_pm4rQ","publishedAt":"2016-04-27T13:58:56.000Z"},
{"guid":"de020e481004","title":"Pszczyna - Zagroda Wsi Pszczyńskiej - skansen (Heritage Park), Polska (Poland)","latlng":"49.978924, 18.950597","youtubeId":"s66o10RIvIM","publishedAt":"2016-06-08T15:10:51.000Z"},
{"guid":"fda665bb1e22","title":"Pszczyna - Park Zamkowy (the Castle Park), Polska (Poland)","latlng":"49.981000, 18.939603","youtubeId":"kbGy0uS7UI0","publishedAt":"2016-04-20T16:26:31.000Z"},
{"guid":"5a99cc08f45c","title":"Kraków Grodzka (the Grodzka Street), Polska (Poland)","latlng":"50.057552, 19.938124","youtubeId":"DLkA0UM9wyY","publishedAt":"2016-04-13T18:02:10.000Z"},
{"guid":"5fa993d8b121","title":"Mollans sur Ouvèze, Provence, France","latlng":"44.237284, 5.191050","youtubeId":"0nNxlx7J37A","publishedAt":"2016-04-06T16:30:38.000Z"},
{"guid":"4adaf6671ed9","title":"Villeneuve-lès-Avignon - Old Town (Vieille Ville), Provence, France","latlng":"43.962957, 4.797082","youtubeId":"XljmlPSsyrA","publishedAt":"2016-03-30T14:28:05.000Z"},
{"guid":"db0855ecafaa","title":"Fort Saint-André - Villeneuve-lès-Avignon, Provence, France","latlng":"43.965737, 4.800563","youtubeId":"uFZ-p1vugAo","publishedAt":"2016-03-23T16:38:58.000Z"},
{"guid":"0eaf59861f9e","title":"Barbakan Kraków (Barbican, Cracow), Polska (Poland)","latlng":"50.065458, 19.941661","youtubeId":"5E6g90JWssI","publishedAt":"2016-03-09T15:03:48.000Z"},
{"guid":"e285bbd80521","title":"Barbakan Kraków (Barbican, Cracow), Polska (Poland) - Extended Version","latlng":"50.065458, 19.941661","youtubeId":"1Hie33W2c0Y","publishedAt":"2016-03-09T15:07:01.000Z"},
{"guid":"6ddc5df161c7","title":"Uzdrowisko Szczawnica (resort town), Polska (Poland)","latlng":"49.427421, 20.486363","youtubeId":"o350h9hoig8","publishedAt":"2016-06-01T16:02:48.000Z"},
{"guid":"875adf9221f8","title":"Gorges de Daluis by car - the whole route, normal speed","latlng":"44.051745, 6.847191","youtubeId":"OF6Z0Iw8QbM","publishedAt":"2016-01-23T16:39:57.000Z"},
{"guid":"a61251147c48","title":"Krupówki Zakopane: sztuka czy kicz? (The Art or Kitsch?), Polska (Poland)","latlng":"49.293902, 19.953754","youtubeId":"oPdjO6-xjAw","publishedAt":"2016-01-27T14:30:04.000Z"},
{"guid":"2d3e86d539f8","title":"Cagnes-sur-Mer (Haut-de-Cagnes), Côte d'Azur (French Riviera), France","latlng":"43.667087, 7.145452","youtubeId":"cSTgBSHsMzY","publishedAt":"2016-02-03T15:31:56.000Z"},
{"guid":"dda83e223b97","title":"Monaco: St Martin Gardens (Les Jardins St Martin)","latlng":"43.730363, 7.423985","youtubeId":"37nED04ZTcs","publishedAt":"2016-03-02T15:27:21.000Z"},
{"guid":"f5fa1dd0f30c","title":"Gréoux-les-Bains, Alpes-de-Haute-Provence, Provence-Alpes-Côte d'Azur, France","latlng":"43.758163, 5.883896","youtubeId":"lzjVDAffG48","publishedAt":"2016-03-16T17:27:38.000Z"},
{"guid":"bf5b5df71ec7","title":"Cotignac, Var, Provence-Alpes-Côte d'Azur, France","latlng":"43.527848, 6.149447","youtubeId":"pOp-0vWa_P4","publishedAt":"2016-02-17T17:31:36.000Z"},
{"guid":"bd5c8dfff1aa","title":"Saint-Tropez - Maritime Museum in the Citadel (Musée Naval de la Citadelle)","latlng":"43.272409, 6.644259","youtubeId":"7NDphsj-1OY","publishedAt":"2016-01-13T14:20:44.000Z"},
{"guid":"7a1c62848e50","title":"Saint-Tropez Citadel (la citadelle de Saint-Tropez), Provence, France","latlng":"43.272409, 6.644259","youtubeId":"1FWE_zYgaRw","publishedAt":"2016-01-06T10:50:45.000Z"},
{"guid":"217ae593e05f","title":"Saint-Raphaël - Old Town and the Sea. French Riviera (Côte d'Azur), France","latlng":"43.425617, 6.769254","youtubeId":"RBzQJWLQJU0","publishedAt":"2016-02-10T16:32:17.000Z"},
{"guid":"a1fa33268ae4","title":"One Day in Vence, French Riviera (Côte d'Azur), France","latlng":"43.722940, 7.113875","youtubeId":"EvjtRi6ctUA","publishedAt":"2016-01-20T17:10:47.000Z"},
{"guid":"140a7e82ed5f","title":"Sukiennice Kraków (the Cloth Hall), Polska (Poland)","latlng":"50.061613, 19.937321","youtubeId":"hYeksMo8Ufw","publishedAt":"2016-02-24T15:27:51.000Z"},
{"guid":"1b9f99a0ca59","title":"Praděd (\"Grandfather\", \"Altvater\", \"Pradziad\"), Czech Republic (Česká republika)","latlng":"50.083604, 17.231367","youtubeId":"b8nFRrsvjbI","publishedAt":"2015-12-23T14:58:28.000Z"},
{"guid":"7281b1190e3e","title":"Jarmark Bożonarodzeniowy (Christmas Market), Rybnik, Polska (Poland)","latlng":"51.109260, 17.032586","youtubeId":"p9tcBi494KQ","publishedAt":"2015-12-16T18:29:04.000Z"},
{"guid":"435d63e18336","title":"Saint-Jeannet,  Alpes-Maritimes, Provence-Alpes-Côte d'Azur, France","latlng":"43.747549, 7.142975","youtubeId":"8_enNw7TO8s","publishedAt":"2015-12-30T15:42:21.000Z"},
{"guid":"40ae82ddbac1","title":"Zamek w Niedzicy i zapora czorsztyńska (Niedzica Castle & the Czorsztyn Dam), Polska","latlng":"53.359686, 20.429588","youtubeId":"OcgdUwnSvf8","publishedAt":"2015-12-09T15:36:42.000Z"},
{"guid":"28eedda56628","title":"Clansayes, Provence, France","latlng":"44.371078, 4.806932","youtubeId":"4z0-g99hjdA","publishedAt":"2015-11-25T17:18:13.000Z"},
{"guid":"122a662793c1","title":"Stary Kościół na Pęksowym Brzyzku (Old Wooden Church), Zakopane, Polska (Poland)","latlng":"49.296888, 19.947033","youtubeId":"flBoI7e_3co","publishedAt":"2015-12-02T18:37:26.000Z"},
{"guid":"5f082e16eb99","title":"Aix-en-Provence - Cours Mirabeau, Provence, France","latlng":"43.526727, 5.448637","youtubeId":"VsK-8DTHQ2w","publishedAt":"2015-11-18T16:28:20.000Z"},
{"guid":"1e6b94cb7998","title":"Aix-en-Provence Sightseeing Tour, Provence-Alpes-Côte d'Azur, France","latlng":"43.529745, 5.447628","youtubeId":"IzU89xs8TEM","publishedAt":"2015-11-11T15:10:46.000Z"},
{"guid":"f83f06856f72","title":"Malaucène, Vaucluse, Provence-Alpes-Côte d'Azur, France","latlng":"44.173483, 5.132376","youtubeId":"DsWKCj6B-CA","publishedAt":"2015-11-04T17:29:00.000Z"},
{"guid":"10c7be2b7d17","title":"Allemagne-en-Provence, Alpes-de-Haute-Provence, France","latlng":"43.781969, 6.006975","youtubeId":"waIWpiJl9HA","publishedAt":"2015-10-21T14:34:41.000Z"},
{"guid":"3e33ce54b134","title":"Warszawa Stare Miasto (Warsaw Old Town), Poland","latlng":"52.249292, 21.011644","youtubeId":"6kTVlQhwQRg","publishedAt":"2015-10-14T15:35:00.000Z"},
{"guid":"951ba45a63b1","title":"Krakowskie Przedmieście (the street), Warszawa, Polska (Warsaw, Poland)","latlng":"52.242550, 21.015062","youtubeId":"_dbpy92KgTg","publishedAt":"2015-10-07T15:05:18.000Z"},
{"guid":"694535131d20","title":"Plac Piłsudskiego, Warszawa, Polska (Pilsudski Square, Warsaw, Poland)","latlng":"52.241912, 21.012128","youtubeId":"c_g2_m0pCAg","publishedAt":"2015-09-22T16:35:06.000Z"},
{"guid":"525a06afcfda","title":"Ramatuelle: The Paillas Windmill (Moulin de Paillas),  Provence, France","latlng":"43.213874, 6.605305","youtubeId":"k1zwf-zSgmg","publishedAt":"2015-09-02T15:31:36.000Z"},
{"guid":"ed82d30aaba3","title":"Saint Nicholas Cathedral in Monaco (Cathédrale de Monaco), Monaco","latlng":"43.730298, 7.422689","youtubeId":"Moq9kxHFFgU","publishedAt":"2015-10-28T17:06:56.000Z"},
{"guid":"8c1937f6763f","title":"La rue des Teinturiers, Avignon, Provence, France","latlng":"43.944971, 4.813711","youtubeId":"A_-tonAejos","publishedAt":"2015-08-26T15:41:04.000Z"},
{"guid":"18772daa21c7","title":"Gattières, Alpes-Maritimes, Provence-Alpes-Côte d'Azur, France","latlng":"43.760784, 7.177845","youtubeId":"apSfUoL9gtU","publishedAt":"2015-09-16T14:31:18.000Z"},
{"guid":"fa1269060960","title":"Pont Van Gogh (Pont Langlois, Van Gogh Bridge), Arles, Provence, France","latlng":"43.656924, 4.620972","youtubeId":"m6VGTyb8RdA","publishedAt":"2015-08-19T15:11:38.000Z"},
{"guid":"6425287adbf9","title":"Fayence in June; Var, Provence-Alpes-Côte d'Azur, France","latlng":"43.623740, 6.694175","youtubeId":"DsIJ31tLQ3w","publishedAt":"2015-08-12T15:06:51.000Z"},
{"guid":"a6205e4446ec","title":"Cannes - Old Town (Vieille Ville Le Suquet) and Old Port, French Riviera, France","latlng":"43.550672, 7.010200","youtubeId":"G22AH0PBY_I","publishedAt":"2015-08-05T15:29:59.000Z"},
{"guid":"1b579ce50feb","title":"Jardin Botanique de la Villa Thuret, Antibes, Côte d'Azur, France","latlng":"43.563981, 7.124193","youtubeId":"iANETTEs12c","publishedAt":"2015-07-29T15:57:08.000Z"},
{"guid":"442423d9cffd","title":"Gorges de l'Ardèche (Ardèche Gorges, Ardèche Canyon), Ardèche, France","latlng":"44.336705, 4.481587","youtubeId":"wHFds-i4lNk","publishedAt":"2015-07-22T14:32:04.000Z"},
{"guid":"9692d7f4ac44","title":"Cicada's sound in Provence (Chant des cigales en Provence), France","latlng":"","youtubeId":"tjrzb7eE8yU","publishedAt":"2015-07-15T14:43:07.000Z"},
{"guid":"d8a14a923255","title":"Demänovská Cave of Liberty (Demänovská jaskyňa slobody), Slovakia (Slovensko)","latlng":"48.998562, 19.585762","youtubeId":"PLvul30_p1Q","publishedAt":"2015-07-01T15:19:17.000Z"},
{"guid":"f30a38243a55","title":"Valréas,  Vaucluse, Provence-Alpes-Côte d'Azur, France","latlng":"44.384135, 4.989857","youtubeId":"Z0t5A6IMR_g","publishedAt":"2015-07-01T15:23:05.000Z"},
{"guid":"5df8409c84e2","title":"Šilheřovice - Castle & Golf Course (Zámek a golfové hřiště), Czech Republic","latlng":"49.925816, 18.274448","youtubeId":"-iglRalkYvo","publishedAt":"2015-06-10T14:48:51.000Z"},
{"guid":"f6e205aa2ef8","title":"Arles - Old Town around the Amphitheatre, Provence, France","latlng":"43.677782, 4.630952","youtubeId":"U0fo295tQVk","publishedAt":"2015-05-25T15:20:30.000Z"},
{"guid":"001f943ea6ac","title":"Ostrava - Old Town (Staré Město), Czech Republic (Česká republika)","latlng":"","youtubeId":"yC_9Lox4QXc","publishedAt":"2015-06-03T14:47:24.000Z"},
{"guid":"ceb01d7a3f49","title":"Pszczyna zamek - wnętrza (Pszczyna Castle: the Interiors), Poland","latlng":"49.978196, 18.940481","youtubeId":"EdSicJU_igY","publishedAt":"2015-05-27T17:56:53.000Z"},
{"guid":"2f7ad3d55095","title":"Carpentras, Vaucluse,  Provence-Alpes-Côte d'Azur, France","latlng":"44.054653, 5.048316","youtubeId":"at5GVgOD4nk","publishedAt":"2015-05-20T15:04:40.000Z"},
{"guid":"984d954111d4","title":"Mandelieu-la-Napoule, Alpes-Maritimes, Provence-Alpes-Côte d'Azur, France","latlng":"43.523300, 6.943002","youtubeId":"oUtk4_DeuWs","publishedAt":"2015-05-13T15:36:15.000Z"},
{"guid":"ca28d217c77f","title":"Carros, Alpes-Maritimes, Provence-Alpes-Côte d'Azur, France","latlng":"43.792416, 7.187448","youtubeId":"eV2pbbntfy0","publishedAt":"2015-04-29T15:57:16.000Z"},
{"guid":"ac5efb464b7f","title":"Fort-Carré - Antibes Juan-les-Pins, Côte d'Azur, France","latlng":"43.590289, 7.127272","youtubeId":"pxo28c9JH8k","publishedAt":"2015-05-06T14:21:48.000Z"},
{"guid":"6fb305af69ed","title":"Boulbon, Bouches-du-Rhône, Provence-Alpes-Côte d'Azur, France","latlng":"43.862789, 4.693471","youtubeId":"XN6QM18IBkE","publishedAt":"2015-04-15T13:34:35.000Z"},
{"guid":"5366d6f84581","title":"Valbonne, Alpes-Maritimes, Provence-Alpes-Côte d'Azur, France","latlng":"43.641487, 7.008920","youtubeId":"kREs1oCjN90","publishedAt":"2015-03-31T17:10:47.000Z"},
{"guid":"5e92a1db881e","title":"La Course Camarguaise (Bullfighting in Camargue style), Camargue, France","latlng":"43.583018, 4.207001","youtubeId":"aDLd1rRqcUk","publishedAt":"2015-04-08T14:43:06.000Z"},
{"guid":"dd6b8b6cad52","title":"Strasbourg Cathedral (Cathédrale de Strasbourg, Straßburger Münster), Alsace France","latlng":"48.581866, 7.751046","youtubeId":"GzMYLJds-48","publishedAt":"2015-03-25T16:43:12.000Z"},
{"guid":"0b977491bf7e","title":"Ravenna, Basilica di San Vitale, Emilia-Romagna, Italy","latlng":"44.420579, 12.196365","youtubeId":"bt5JiCsqiZM","publishedAt":"2015-03-17T16:05:12.000Z"},
{"guid":"dc355174f46d","title":"Arles - Ancient Roman Theatre (Théâtre Antique d’Arles), Provence, France","latlng":"43.676507, 4.629837","youtubeId":"27_0V6KasEc","publishedAt":"2015-03-11T17:05:19.000Z"},
{"guid":"eb3e4be2a7d4","title":"Abbaye Saint-Michel de Frigolet revisited, Provence, France","latlng":"43.858305, 4.728066","youtubeId":"J1-FQb7uYrw","publishedAt":"2015-04-01T15:41:17.000Z"},
{"guid":"29f806bc5854","title":"Arles - the Roman Amphitheatre (Arènes d'Arles), Provence, France","latlng":"43.677614, 4.630985","youtubeId":"TVynEnmocMk","publishedAt":"2015-02-25T15:29:18.000Z"},
{"guid":"edf28248ec66","title":"Feldkirchen in Kärnten, Carinthia, Austria (Österreich)","latlng":"46.725821, 14.089148","youtubeId":"53iqW38TUeo","publishedAt":"2015-03-04T15:47:45.000Z"},
{"guid":"9babe683091d","title":"Esparron-de-Verdon, Alpes-de-Haute-Provence, Provence-Alpes-Côte d'Azur, France","latlng":"43.739090, 5.973687","youtubeId":"yurxfMd7tTA","publishedAt":"2015-02-18T15:43:40.000Z"},
{"guid":"17e1cb307531","title":"Arles - Invasion of Romans (the Arelate Festival), Provence, France","latlng":"43.677550, 4.630898","youtubeId":"HcvfTSnPwj0","publishedAt":"2015-02-11T16:26:02.000Z"},
{"guid":"f8f4d115d983","title":"Sète, Hérault, Languedoc-Roussillon, France","latlng":"43.402847, 3.701452","youtubeId":"kXhzkrYcE6I","publishedAt":"2015-03-18T15:05:24.000Z"},
{"guid":"81cf9cc97814","title":"A red sunset in Vilsbiburg, Bavaria, Germany","latlng":"48.450367, 12.352759","youtubeId":"0HJW1AvMCx0","publishedAt":"2015-02-04T14:55:07.000Z"},
{"guid":"3bbaa6f5cbb4","title":"Antibes - The Path around the Cap D'Antibes, French Riviera, France","latlng":"43.552316, 7.144237","youtubeId":"fchyUyo8a40","publishedAt":"2015-01-28T18:59:11.000Z"},
{"guid":"ed46501ee22b","title":"Zlín - Zoo, Czech Republic (Česká republika)","latlng":"49.271639, 17.714727","youtubeId":"OK1_We0HACI","publishedAt":"2015-01-21T15:23:46.000Z"},
{"guid":"068422f1eb59","title":"Saint-Paul-de-Vence,  Alpes-Maritimes, Provence-Alpes-Côte d'Azur, France","latlng":"43.696971, 7.122249","youtubeId":"ky2RSd8ITnQ","publishedAt":"2015-01-12T19:21:03.000Z"},
{"guid":"7fdacc6b3b26","title":"Sommières, Gard, Languedoc-Roussillon, France","latlng":"43.783608, 4.088633","youtubeId":"-4nuQ7s9z3I","publishedAt":"2015-01-14T18:00:51.000Z"},
{"guid":"069188942966","title":"Basilica di Sant'Apollinare in Classe - Ravenna, Italy","latlng":"44.380214, 12.232317","youtubeId":"qd3KSW2st-c","publishedAt":"2015-01-06T10:34:46.000Z"},
{"guid":"d3670ba5590f","title":"Merry Christmas 2014!","latlng":"","youtubeId":"P1ujAp0zJws","publishedAt":"2014-12-23T11:10:42.000Z"},
{"guid":"61a671d4fbf5","title":"One day in Mougins, Alpes-Maritimes, Provence-Alpes-Côte d'Azur, France","latlng":"43.600835, 6.995129","youtubeId":"IcpgbyD0l8Q","publishedAt":"2014-12-31T13:03:38.000Z"},
{"guid":"6096c9c5ab38","title":"Biot, Alpes-Maritimes, Provence-Alpes-Côte d'Azur, France","latlng":"43.627497, 7.098149","youtubeId":"nXiJGjkUdOI","publishedAt":"2014-12-17T17:53:27.000Z"},
{"guid":"199217d70f6b","title":"Gassin, Var, Provence-Alpes-Côte d'Azur, France","latlng":"43.252600, 6.572813","youtubeId":"Dr3MZd4iI1c","publishedAt":"2014-11-13T18:58:34.000Z"},
{"guid":"e889651b1393","title":"Hotel Club I Pini - Residenza D'Epoca, Lido di Camaiore, Tuscany, Italy","latlng":"43.892379, 10.230945","youtubeId":"rgB9lh4EuVc","publishedAt":"2014-11-19T17:43:18.000Z"},
{"guid":"b6fb473c361f","title":"Lido di Camaiore, Province of Lucca, Tuscany, Italy","latlng":"43.894342, 10.222479","youtubeId":"x3OcWuT7xIo","publishedAt":"2014-11-12T16:26:26.000Z"},
{"guid":"ceeb39dd83e3","title":"Aups, Var, Provence-Alpes-Côte d'Azur, France","latlng":"43.627482, 6.223727","youtubeId":"s63Ed-Hqow8","publishedAt":"2015-01-28T19:01:02.000Z"},
{"guid":"cd756a8ed58a","title":"Glanum (Saint Rémy de Provence), Provence-Alpes-Côte d'Azur, France","latlng":"43.773583, 4.833031","youtubeId":"ELrDJrgXyoI","publishedAt":"2014-11-05T15:52:57.000Z"},
{"guid":"9a9c51c7b80b","title":"Salernes, Var, Provence-Alpes-Côte d'Azur, France","latlng":"43.565206, 6.232142","youtubeId":"oRpTKkKHvo0","publishedAt":"2014-12-10T15:49:32.000Z"},
{"guid":"2d3937207c31","title":"Sault,  Vaucluse, Provence-Alpes-Côte d'Azur, France","latlng":"44.091744, 5.408170","youtubeId":"kAJLbdFlM5o","publishedAt":"2014-12-03T15:51:30.000Z"},
{"guid":"d238c63a42c1","title":"Vallauris, Alpes-Maritimes, Provence-Alpes-Côte d'Azur, France","latlng":"43.579560, 7.051816","youtubeId":"2jyrD6srnIA","publishedAt":"2015-01-07T15:31:42.000Z"},
{"guid":"ab77497f7dbe","title":"Golfe-Juan, Alpes-Maritimes, Provence-Alpes-Côte d'Azur, France","latlng":"43.566652, 7.077932","youtubeId":"SR34TtPpNBM","publishedAt":"2014-10-29T15:02:47.000Z"},
{"guid":"0fdc1b206c1d","title":"Colmar, Alsace (das Elsass), France","latlng":"48.077769, 7.357984","youtubeId":"Phy0O_mOlSE","publishedAt":"2014-11-26T14:52:08.000Z"},
{"guid":"69ec29262f78","title":"Avignon, Vaucluse, Provence-Alpes-Côte d'Azur, France","latlng":"43.948102, 4.807331","youtubeId":"FvLlxxF5WKc","publishedAt":"2014-10-22T17:13:44.000Z"},
{"guid":"40e2ba2bd253","title":"Camargue, Bouches-du-Rhône, Provence-Alpes-Côte d'Azur, France","latlng":"43.497831, 4.565207","youtubeId":"DdjWdRs0IOs","publishedAt":"2014-10-08T15:40:20.000Z"},
{"guid":"44e1588b20ad","title":"Abbaye de Montmajour, Bouches-du-Rhône, Provence-Alpes-Côte d'Azur, France","latlng":"43.705563, 4.663846","youtubeId":"SIlRQQOr1nM","publishedAt":"2014-09-24T13:18:18.000Z"},
{"guid":"70b2217996ff","title":"Strasbourg, Alsace (Straßburg, das Elsass), France","latlng":"48.581132, 7.747759","youtubeId":"JeFP4Tj08yY","publishedAt":"2014-09-17T14:36:49.000Z"},
{"guid":"a4c7610c287d","title":"Valensole, Alpes-de-Haute-Provence, Provence-Alpes-Côte d'Azur, France","latlng":"43.837498, 5.983642","youtubeId":"jaxkASaUMRg","publishedAt":"2014-08-20T14:23:08.000Z"},
{"guid":"ae69b2418de9","title":"Malenovice,  Frýdek-Místek District, Moravian-Silesian Region, Czech republic","latlng":"49.572864, 18.408421","youtubeId":"XDhJwXSqbRM","publishedAt":"2014-08-27T14:04:04.000Z"},
{"guid":"e128d63a26dd","title":"Exercises for Water Bombers (Firefighters), Provence-Alpes-Côte d'Azur, France","latlng":"43.418571, 6.758973","youtubeId":"HM3lZyU3VT4","publishedAt":"2014-08-13T14:28:28.000Z"},
{"guid":"5be66b85aa6e","title":"La lavande / lavender fields in Provence, Alpes-de-Haute-Provence, France","latlng":"43.872929, 6.024475","youtubeId":"utPMwnHZvP4","publishedAt":"2014-08-06T14:12:23.000Z"},
{"guid":"6cd803b3a6dc","title":"Guillaumes, Alpes-Maritimes, Provence-Alpes-Côte d'Azur, France","latlng":"44.090033, 6.853984","youtubeId":"ycZfeAts1Fs","publishedAt":"2014-07-30T13:35:14.000Z"},
{"guid":"db8ccc0f04d8","title":"Gorges de Daluis (viewpoints & timelapse), Provence-Alpes-Côte d'Azur, France","latlng":"44.052301, 6.845475","youtubeId":"WBsGJ7BB864","publishedAt":"2014-07-23T17:22:59.000Z"},
{"guid":"5cf4aa2d86e8","title":"The Var Valley - Vallée du Var, Provence-Alpes-Côte d'Azur, France","latlng":"43.840780, 7.195200","youtubeId":"WaWjuPv-XK4","publishedAt":"2014-07-16T13:38:07.000Z"},
{"guid":"9681168bdb22","title":"Villecroze, Var, Provence-Alpes-Côte d'Azur; France","latlng":"43.582298, 6.275768","youtubeId":"Kp_HIDTwCGE","publishedAt":"2014-07-09T13:54:34.000Z"},
{"guid":"7acf9b3bf723","title":"Le Bar-sur-Loup, Provence-Alpes-Côte d'Azur, France","latlng":"43.701286, 6.990042","youtubeId":"gW5fwryFcTw","publishedAt":"2014-09-10T14:29:43.000Z"},
{"guid":"edbe5fa15e96","title":"Pasquini Castle in Castiglioncello and Populonia, Tuscany, Italy","latlng":"43.405384, 10.412792","youtubeId":"hXbBelUtkQE","publishedAt":"2014-05-25T13:16:46.000Z"},
{"guid":"c2c31bcfc287","title":"Roquebrune-Cap-Martin, Alpes-Maritimes, Provence-Alpes-Côte d'Azur, France","latlng":"43.755525, 7.476318","youtubeId":"YJPEcuigyug","publishedAt":"2014-07-02T11:30:54.000Z"},
{"guid":"87a86fb45caa","title":"Gilette, Alpes-Maritimes, Provence-Alpes-Côte d'Azur, France","latlng":"43.849926, 7.161901","youtubeId":"7yeVKcsAyH0","publishedAt":"2014-05-28T16:14:48.000Z"},
{"guid":"6bc7d300c7a6","title":"3 zámky u Ostravy (3 palaces near Ostrava), Česká republika (Czech Republic)","latlng":"49.820606, 18.264859","youtubeId":"fRijP0ZDUYI","publishedAt":"2014-06-10T13:33:23.000Z"},
{"guid":"6760e22d99c6","title":"Sigale,  Alpes-Maritimes, Provence-Alpes-Côte d'Azur, France","latlng":"43.871869, 6.964116","youtubeId":"x85dyjIG4IQ","publishedAt":"2014-06-04T14:22:21.000Z"},
{"guid":"754d9f64f53d","title":"Montauroux (Var), Provence-Alpes-Côte d'Azur, France","latlng":"43.618071, 6.764553","youtubeId":"McCToBXKF7g","publishedAt":"2014-10-15T14:46:32.000Z"},
{"guid":"3a0f4fea6285","title":"Sainte-Croix-du-Verdon, Provence-Alpes-Côte d'Azur, France","latlng":"43.759022, 6.151336","youtubeId":"SLVdqYqHHIU","publishedAt":"2014-10-01T14:09:05.000Z"},
{"guid":"c922d3b6f389","title":"Villach, Kärnten, Österreich (Carinthia, Austria)","latlng":"46.608177, 13.849980","youtubeId":"3dIEW6RQ-Yc","publishedAt":"2014-05-21T13:43:40.000Z"},
{"guid":"551c7d0800da","title":"Carcès (Var), Provence-Alpes-Côte d'Azur, France","latlng":"43.476342, 6.182702","youtubeId":"9PpUtTlSV9o","publishedAt":"2014-05-07T14:08:03.000Z"},
{"guid":"1c12fbf81c48","title":"Ostrava - Zoo, Czech Republic (Česká republika)","latlng":"49.843648, 18.319241","youtubeId":"xwew8vEr_xA","publishedAt":"2014-05-14T13:29:28.000Z"},
{"guid":"1c423824ff3e","title":"Callian (Var), Provence-Alpes-Côte d'Azur, France","latlng":"43.622567, 6.753216","youtubeId":"97tIVtmboMI","publishedAt":"2014-04-23T14:07:59.000Z"},
{"guid":"b015ad3e9515","title":"Olomouc, Czech Republic (Česká republika)","latlng":"49.594057, 17.251639","youtubeId":"eMcIvKzSIVo","publishedAt":"2014-03-27T17:50:54.000Z"},
{"guid":"fcaf96354e4a","title":"Fontaine-de-Vaucluse - walking to the source (Provence, France)","latlng":"43.921744, 5.127938","youtubeId":"SS1OAeCXJ0I","publishedAt":"2014-04-30T16:44:54.000Z"},
{"guid":"091f7adcf50a","title":"Saint-Saturnin-lès-Apt, Provence, France","latlng":"43.942719, 5.382640","youtubeId":"6_6qWMUXXy0","publishedAt":"2014-04-09T15:46:45.000Z"},
{"guid":"28180dbaccf4","title":"Simiane-la-Rotonde - inside the village, Provence, France","latlng":"43.981037, 5.562955","youtubeId":"bxjIQcmCCzs","publishedAt":"2014-03-26T15:59:40.000Z"},
{"guid":"cc9e58464a5f","title":"Camera Car Mount Review - Simple and cheap but effective solution","latlng":"","youtubeId":"kUeNWVFH9Xo","publishedAt":"2014-03-19T05:56:33.000Z"},
{"guid":"071b841020d4","title":"Amazing Ochre Land - Colorado Provençal de Rustrel, Provence, France","latlng":"43.919972, 5.499056","youtubeId":"ecJnXRitam4","publishedAt":"2014-03-12T15:27:28.000Z"},
{"guid":"376da7dee4a3","title":"Abbaye Saint-Michel de Frigolet (Provence; France). A concert of medieval music","latlng":"43.858274, 4.728249","youtubeId":"rSpfoMzulAY","publishedAt":"2014-03-12T15:28:24.000Z"},
{"guid":"fe38caf6bfa4","title":"Cieszyn zimą (Cieszyn in the Winter), Silesia, Southern Poland","latlng":"49.749514, 18.631360","youtubeId":"HmTAv8CrEvc","publishedAt":"2014-02-12T16:12:07.000Z"},
{"guid":"684e5a3d90e8","title":"Castle Hradec nad Moravicí in the Winter, Czech Republic","latlng":"49.865814, 17.877953","youtubeId":"fB6JpCAR8kc","publishedAt":"2014-02-05T16:27:20.000Z"},
{"guid":"cc83da279f05","title":"Driving in French Alps (Maritime Alps; Alpes-Maritimes), southern France","latlng":"43.801369, 6.907410","youtubeId":"2f6KT3ArP10","publishedAt":"2014-02-26T14:56:50.000Z"},
{"guid":"ee2afdcbd0bf","title":"Gréolières, Alpes-Maritimes (Maritime Alps), French Riviera - France","latlng":"43.795297, 6.943413","youtubeId":"7923b_VYjZA","publishedAt":"2014-02-12T16:12:37.000Z"},
{"guid":"31e401668b8e","title":"Aiguines and the Castle of Aiguines (Château d'Aiguines), southern France","latlng":"43.775496, 6.242236","youtubeId":"LtIHPFjSItE","publishedAt":"2014-03-05T14:39:37.000Z"},
{"guid":"cb667038c005","title":"Kraków: zamek królewski na Wawelu (Cracow: Wawel Royal Castle on Wawel Hill), Poland","latlng":"50.054043, 19.935455","youtubeId":"zxyxgbcm5Mg","publishedAt":"2014-02-05T15:30:02.000Z"},
{"guid":"ff0526f91b27","title":"Kraków: rynek i Stare Miasto (Cracow: Main Square and Old Town), Poland","latlng":"50.061883, 19.936800","youtubeId":"yMv816ALk8Q","publishedAt":"2014-01-29T15:01:45.000Z"},
{"guid":"5f7bb0524980","title":"Bieszczady jesienią: Dwernik Kamień (Holica) (Bieszczady Mountains in autumn)","latlng":"49.191624, 22.581445","youtubeId":"SwOqCaDjAgI","publishedAt":"2014-03-05T14:37:30.000Z"},
{"guid":"c5827e14daee","title":"Bieszczady jesienią: Wołosate, Tarnica, Ustrzyki Górne","latlng":"49.074576, 22.726099","youtubeId":"79oY8v8wFMQ","publishedAt":"2014-02-05T15:10:41.000Z"},
{"guid":"48f306a50cf8","title":"Bieszczady jesienią: Ustrzyki Górne, Połonina Caryńska, Brzegi Górne","latlng":"49.107787, 22.650311","youtubeId":"IXhXZvMoV_Q","publishedAt":"2014-01-30T06:03:51.000Z"},
{"guid":"64647e89f07c","title":"Bieszczady jesienią: Brzegi Górne, Połonina Wetlińska, Wetlina","latlng":"49.142492, 22.568407","youtubeId":"o11LXgs_Ljg","publishedAt":"2014-01-22T15:07:20.000Z"},
{"guid":"6017d60b1529","title":"Rybnik - szopka bożonarodzeniowa (Christmas Nativity Scenes in Rybnik), Poland","latlng":"50.096826, 18.536906","youtubeId":"6gjRtimHvm0","publishedAt":"2013-12-28T19:05:54.000Z"},
{"guid":"8881f3402b0d","title":"Quick Tour of Monaco in mini-train, French Riviera (Côte d'Azur)","latlng":"43.739633, 7.427709","youtubeId":"6PYG8Duk4mg","publishedAt":"2014-01-08T15:02:40.000Z"},
{"guid":"50822fb4cd7e","title":"Sainte-Maxime, French Riviera, France","latlng":"43.307955, 6.636193","youtubeId":"TrbDaIwmv_w","publishedAt":"2014-04-16T14:11:57.000Z"},
{"guid":"cd43bd52fdb4","title":"Raduň Castle in December, Czech Republic (Česká Republika)","latlng":"49.891239, 17.944602","youtubeId":"1oRM15iIuHw","publishedAt":"2013-12-18T15:27:15.000Z"},
{"guid":"6f6df4a28843","title":"La Turbie with some views of Monaco, French Riviera, France","latlng":"43.744864, 7.401779","youtubeId":"zmkLnAcFVps","publishedAt":"2014-02-19T15:19:06.000Z"},
{"guid":"2217155f3233","title":"Menton, Val Rahmeh Botanical Garden, French Riviera, France","latlng":"43.774129, 7.499904","youtubeId":"CLiZtlGCCf0","publishedAt":"2014-01-15T14:36:36.000Z"},
{"guid":"89cbc50945c6","title":"Domaine du Château d'Estoublon in June; Provence, France","latlng":"43.733519, 4.740705","youtubeId":"orwAhpU6zUI","publishedAt":"2013-12-04T15:15:59.000Z"},
{"guid":"5549ae907956","title":"Entrevaux, Alpes de Haute Provence, Southern France","latlng":"43.950139, 6.810681","youtubeId":"-_xuplTywCg","publishedAt":"2013-11-26T16:57:03.000Z"},
{"guid":"d6fadccd293a","title":"Gourdon, French Riviera, France","latlng":"43.719902, 6.978252","youtubeId":"nVE0IhlvXqE","publishedAt":"2013-12-11T14:56:47.000Z"},
{"guid":"cfab08d128f0","title":"Abbaye du Thoronet, Provence, France","latlng":"43.460343, 6.263941","youtubeId":"ZFWBTmrt1Bg","publishedAt":"2013-12-25T15:18:24.000Z"},
{"guid":"398d53d96d13","title":"Monteriggioni, Tuscany (Toscana), Italy (Italia)","latlng":"43.390041, 11.223119","youtubeId":"2jv99N93yoA","publishedAt":"2013-11-20T14:58:11.000Z"},
{"guid":"273b1b5cf453","title":"Cortona, Tuscany (Toscana), Italy (Italia)","latlng":"43.275073, 11.985473","youtubeId":"80RYcmGJ9zc","publishedAt":"2013-11-13T15:14:44.000Z"},
{"guid":"b5303dd78e3b","title":"Montalcino, Tuscany (Toscana), Italy (Italia)","latlng":"43.057122, 11.490132","youtubeId":"sk5TS5tGWhY","publishedAt":"2013-11-07T18:06:24.000Z"},
{"guid":"505d1d17dffe","title":"Bolsena, Lazio, Italy (Italia)","latlng":"42.643254, 11.984534","youtubeId":"KSfus5Ga_l4","publishedAt":"2013-10-29T15:32:52.000Z"},
{"guid":"bb247f17195e","title":"Montepulciano, Tuscany (Toscana), Italy (Italia)","latlng":"43.096907, 11.785104","youtubeId":"0vs7tyBDzws","publishedAt":"2013-10-21T16:54:26.000Z"},
{"guid":"bd5b4614c8b0","title":"Beautiful Fire Salamander, Korbielów, Poland","latlng":"49.567274, 19.350381","youtubeId":"84T5vYBIFhE","publishedAt":"2013-09-27T15:34:52.000Z"},
{"guid":"6ee708789213","title":"Pienza, Tuscany (Toscana), Italy (Italia)","latlng":"43.077973, 11.676370","youtubeId":"2LaZS297kec","publishedAt":"2013-10-15T17:05:04.000Z"},
{"guid":"f87e62533607","title":"Abbazia di Sant'Antimo, Tuscany (Toscana), Italy (Italia)","latlng":"42.999609, 11.515576","youtubeId":"c2v6qHglvn4","publishedAt":"2013-09-22T16:58:31.000Z"},
{"guid":"3c0ff74fee77","title":"Castiglione del Lago (Lake Trasimeno), Umbria, Italy (Italia)","latlng":"43.126252, 12.048305","youtubeId":"KWV4T5Wn0fY","publishedAt":"2013-10-08T15:50:02.000Z"},
{"guid":"452bbc15a20d","title":"Assisi, Umbria, Italy (Italia)","latlng":"43.070353, 12.616341","youtubeId":"-C9NByHI-DA","publishedAt":"2013-10-03T14:55:49.000Z"},
{"guid":"6354d2adefa9","title":"Orvieto, Umbria, Italy (Italia)","latlng":"42.719100, 12.110492","youtubeId":"2TN1-x00z4Q","publishedAt":"2013-10-29T15:33:09.000Z"},
{"guid":"6a933f191010","title":"Siena - She-Wolf Contrada (Contrada della Lupa) of Siena, Tuscany (Toscana), Italy HD","latlng":"43.319687, 11.329880","youtubeId":"LrPsiCMx9yk","publishedAt":"2013-09-27T15:10:41.000Z"},
{"guid":"583c56331430","title":"San Gimignano - the medieval Manhattan, Tuscany (Toscana), Italy (Italia)","latlng":"43.468352, 11.042916","youtubeId":"NenFpFK3P38","publishedAt":"2013-09-14T18:40:01.000Z"},
{"guid":"e457ecef6783","title":"Siena, Tuscany (Toscana), Italy (Italia)","latlng":"43.321873, 11.324559","youtubeId":"GTDr84Gy3jA","publishedAt":"2013-09-17T16:49:14.000Z"},
{"guid":"8d79fc78727b","title":"Antibes - From Clouds to Sun in a few hours, French Riviera - France","latlng":"43.581004, 7.126135","youtubeId":"980F5vLhBzU","publishedAt":"2014-01-01T16:20:05.000Z"},
{"guid":"184f2b71973e","title":"Saint-Tropez - Around the Citadel, French Riviera, France","latlng":"43.272116, 6.643916","youtubeId":"K1cpRS3udI0","publishedAt":"2013-09-04T11:00:17.000Z"},
{"guid":"fc97fc7df133","title":"Nice - The streets of Old Town (Vieux-Nice), French Riviera, France","latlng":"43.697018, 7.275206","youtubeId":"ntuvVC5Uej8","publishedAt":"2013-08-28T16:59:56.000Z"},
{"guid":"db60c59b86f4","title":"Nice - The Castle Hill (Colline du Chateau), French Riviera, France","latlng":"43.695715, 7.280055","youtubeId":"Xx_7vGAIaM4","publishedAt":"2013-08-25T16:43:41.000Z"},
{"guid":"eb35b3e67189","title":"Nice - Cours Saleya Flower Market (Marché aux Fleurs), French Riviera, France","latlng":"43.695350, 7.275281","youtubeId":"sr8pjUG9Qz4","publishedAt":"2013-08-21T14:19:56.000Z"},
{"guid":"705c8ec40f21","title":"Saint-Jean-Cap-Ferrat and Cap Ferrat, French Riviera, France","latlng":"43.676000, 7.329410","youtubeId":"hZOqh4Jubnw","publishedAt":"2013-08-13T15:44:46.000Z"},
{"guid":"ad758a6f056a","title":"Grimaud - The Castle and the Mill, French Riviera, France","latlng":"43.274831, 6.520900","youtubeId":"f_ciu707dMI","publishedAt":"2013-08-07T14:12:55.000Z"},
{"guid":"75a2d9193f1a","title":"Grimaud - The Village, French Riviera, France","latlng":"43.273636, 6.521436","youtubeId":"WXTr7iBuj8Q","publishedAt":"2013-08-03T13:00:05.000Z"},
{"guid":"74e63030f4c9","title":"Port Grimaud (French Venice), French Riviera, France","latlng":"43.272147, 6.578415","youtubeId":"LPiWSomC58M","publishedAt":"2013-07-28T11:07:14.000Z"},
{"guid":"319f0faa44b3","title":"Mont Ventoux - the Giant of Provence, southern France","latlng":"44.174095, 5.278464","youtubeId":"aehmQajwhw4","publishedAt":"2013-07-14T17:14:39.000Z"},
{"guid":"7b399b643ede","title":"Moustiers-Sainte-Marie, Regional Natural Park of Verdon, South France","latlng":"43.847012, 6.222096","youtubeId":"vJ9OHj3ItvQ","publishedAt":"2013-07-21T06:24:56.000Z"},
{"guid":"e22414c37c01","title":"Verdon Gorge (Gorges du Verdon, Grand Canyon du Verdon), South France","latlng":"43.752415, 6.378767","youtubeId":"fH6Be3DHvlg","publishedAt":"2013-07-09T16:38:25.000Z"},
{"guid":"9424a19554c7","title":"Nice - Beach and the Promenade des Anglais. French Riviera, France","latlng":"43.693027, 7.255955","youtubeId":"4rY4PlSCy48","publishedAt":"2013-07-03T15:04:46.000Z"},
{"guid":"03f60f076019","title":"Zbrasov Aragonite Caves (Zbrašovské aragonitové jeskyně), Czechia ","latlng":"49.531687, 17.745712","youtubeId":"EBfBJa8H65U","publishedAt":"2014-03-19T15:12:16.000Z"},
{"guid":"24e032b0f1c5","title":"Štramberk - Botanic garden and arboretum, Czech Republic","latlng":"49.588299, 18.125563","youtubeId":"KqpabvdDkrM","publishedAt":"2013-06-04T17:50:11.000Z"},
{"guid":"ce975165d03c","title":"Štramberk - The \"Štramberská Trúba\" Tower, Czech Republic","latlng":"49.592404, 18.115868","youtubeId":"IfcV5NXWUuQ","publishedAt":"2013-06-30T16:10:11.000Z"},
{"guid":"f82ce431b754","title":"Štramberk, Moravia, Czech Republic - Česko","latlng":"49.590568, 18.114752","youtubeId":"zjOWe6XRcLE","publishedAt":"2013-05-07T16:17:41.000Z"},
{"guid":"fcdfd4413f7f","title":"Abbaye Saint-Michel de Frigolet, Provence, France","latlng":"43.858251, 4.728174","youtubeId":"uTRq4JEq3FE","publishedAt":"2013-04-29T15:47:55.000Z"},
{"guid":"3cf7cd9a84f1","title":"Zlatorudné mlýny (Gold Ore Mills), Zlaté Hory, Czech Republic","latlng":"50.251366, 17.366606","youtubeId":"JhXQ-lhKsx0","publishedAt":"2013-04-24T17:15:40.000Z"},
{"guid":"3e1e0977ac39","title":"Rejvíz - Velké mechové jezírko (Great Moss Lake), Czech Republic","latlng":"50.219752, 17.286796","youtubeId":"1VSPkoaVwRw","publishedAt":"2013-04-19T15:18:09.000Z"},
{"guid":"991887b1de2c","title":"Ramatuelle, French Riviera, France","latlng":"43.215089, 6.612869","youtubeId":"ppDLWMaRyvo","publishedAt":"2013-04-09T08:27:15.000Z"},
{"guid":"a43c36e7ee71","title":"South Poland - After Snow Disaster (April 2, 2013)","latlng":"","youtubeId":"scRR_dGLnXg","publishedAt":"2013-04-02T18:20:34.000Z"},
{"guid":"69a897c94b6f","title":"San Marino City, San Marino","latlng":"43.935998, 12.447306","youtubeId":"g9-1ZOpV3NE","publishedAt":"2013-04-06T17:07:07.000Z"},
{"guid":"ed74d4982aa3","title":"Kroměříž - The Flower Garden (Květná zahrada), Czech Republic","latlng":"49.297450, 17.383087","youtubeId":"sY0jKHBmRKQ","publishedAt":"2013-04-30T10:38:54.000Z"},
{"guid":"1e8713bd319c","title":"Kroměříž - Old Town, Czech Republic","latlng":"49.300007, 17.393423","youtubeId":"IDOF8lr8sic","publishedAt":"2013-05-20T14:35:55.000Z"},
{"guid":"fe76a859f23f","title":"Kroměříž - Squirrels eating and playing, Czech Republic","latlng":"49.294872, 17.397350","youtubeId":"lYDer72DO_Y","publishedAt":"2013-03-27T19:49:20.000Z"},
{"guid":"7f62cac107f9","title":"Karlova Studánka Spa Resort, Czech Republic","latlng":"50.073490, 17.306176","youtubeId":"I9jOy_JeWKY","publishedAt":"2013-03-23T14:41:28.000Z"},
{"guid":"bac667457108","title":"Litomyšl,  Pardubice Region, Czech Republic","latlng":"49.872665, 16.311881","youtubeId":"vILHMiJk4go","publishedAt":"2013-03-10T15:24:47.000Z"},
{"guid":"ddd9c856d5fc","title":"Goats and sheeps in Nový Dvůr, Czech Republic","latlng":"49.984553, 12.984743","youtubeId":"atQ11bjQ784","publishedAt":"2013-03-05T17:43:19.000Z"},
{"guid":"116552453c6f","title":"Between Agay and Le Dramont, French Riviera, France","latlng":"43.426921, 6.858020","youtubeId":"rIeWXKI86jk","publishedAt":"2013-02-26T19:21:33.000Z"},
{"guid":"6854dcb843c3","title":"Le Lavandou - The Coast, French Riviera, France","latlng":"43.138179, 6.369638","youtubeId":"d6LLRP_HsJM","publishedAt":"2013-02-24T17:51:29.000Z"},
{"guid":"ac8304ee61ba","title":"Sausset-les-Pins - the marina coast, France, Provence","latlng":"43.331275, 5.108871","youtubeId":"cgktbazljaw","publishedAt":"2013-02-20T15:26:28.000Z"},
{"guid":"db47bd64f54b","title":"Cornillon-Confoux, France, Provence","latlng":"43.562783, 5.071280","youtubeId":"VDrlwjfxzTk","publishedAt":"2013-02-17T14:32:33.000Z"},
{"guid":"1c5467940163","title":"Barbentane, Provence, southern France","latlng":"43.899241, 4.747277","youtubeId":"A3iTdweOHgk","publishedAt":"2013-02-05T19:42:54.000Z"},
{"guid":"c709fc3fd3d3","title":"Nový Dvůr - Arboretum, Czech Republic","latlng":"49.934258, 17.772733","youtubeId":"H5DpDoXdDEk","publishedAt":"2013-03-05T15:54:32.000Z"},
{"guid":"fc0fa2b88068","title":"Hradec nad Moravici, The castle and the forest, Czech Republic","latlng":"49.865071, 17.874534","youtubeId":"u1eiJ6oANzc","publishedAt":"2013-03-19T08:46:44.000Z"},
{"guid":"c9746b2b05e6","title":"Hradec nad Moravicí - Old Cars Gathering, Czech Republic","latlng":"49.865071, 17.874534","youtubeId":"B8waEQFw4gs","publishedAt":"2013-01-28T14:37:32.000Z"},
{"guid":"8a504fff3f9f","title":"Nové Hrady, the castle, Pardubický kraj, Czech Republic","latlng":"49.852498, 16.145622","youtubeId":"Z-Z6y4SObVk","publishedAt":"2013-02-02T08:33:08.000Z"},
{"guid":"e65401987eae","title":"Raduň, the castle - Winter, Moravskoslezský kraj, Czech Republic","latlng":"49.891211, 17.944452","youtubeId":"9yycGLzU5_I","publishedAt":"2013-01-13T20:27:20.000Z"},
{"guid":"0334bb321c5d","title":"Raduň, the castle - Spring, Moravskoslezský kraj, Czech Republic","latlng":"49.891211, 17.944452","youtubeId":"bgcDUrR--z8","publishedAt":"2013-02-02T08:24:35.000Z"},
{"guid":"d1764c815f0e","title":"Raduň, The Castle - Early Spring, Moravskoslezský kraj, Czech Republic","latlng":"49.891211, 17.944452","youtubeId":"z43tLrBznmQ","publishedAt":"2013-01-22T15:23:23.000Z"},
{"guid":"c1106f068db1","title":"Kravaře - Early spring (časné jaro), Moravskoslezský kraj, Czech Republic","latlng":"49.932254, 18.004645","youtubeId":"Z7dU8GUIDCU","publishedAt":"2013-01-18T08:04:42.000Z"},
{"guid":"669912b9bdb8","title":"Grambois, Luberon, Provence, France","latlng":"43.762609, 5.588488","youtubeId":"rYNDU3wmB1U","publishedAt":"2013-01-08T16:35:20.000Z"},
{"guid":"da36bb655f6e","title":"Lourmarin, Luberon, Provence, France","latlng":"43.763946, 5.362570","youtubeId":"QdPF87kNMsA","publishedAt":"2013-01-08T16:08:44.000Z"},
{"guid":"48d2d07dd7be","title":"Tarascon, Provence, France","latlng":"43.805702, 4.660262","youtubeId":"Q-LE_K4B3qw","publishedAt":"2013-01-07T17:48:05.000Z"},
{"guid":"e0ffa2ecc74e","title":"Menerbes, Provence, Luberon, France","latlng":"43.832512, 5.206376","youtubeId":"tBIOgA9m8y4","publishedAt":"2013-01-07T16:05:28.000Z"},
{"guid":"245657c9b85d","title":"Isle sur la Sorgue, Provence, France","latlng":"43.919497, 5.051154","youtubeId":"boJyuJF2wQw","publishedAt":"2013-01-06T15:19:48.000Z"},
{"guid":"be1c8ac052cd","title":"Aigues-Mortes, Languedoc-Roussillon, Camargue, France","latlng":"43.566659, 4.191138","youtubeId":"Vu7WbAbJwF4","publishedAt":"2013-01-06T07:39:35.000Z"},
{"guid":"c8422f230a22","title":"Bonnieux, Luberon, Provence, France","latlng":"43.823093, 5.307295","youtubeId":"1XQ3sTNvDFE","publishedAt":"2013-01-05T12:40:37.000Z"},
{"guid":"b394a4615915","title":"Uzes, Languedoc-Roussillon, France","latlng":"44.012172, 4.419638","youtubeId":"Q1G1AoeHjAE","publishedAt":"2013-01-04T19:45:44.000Z"},
{"guid":"323fe994e36a","title":"Nimes, Languedoc-Roussillon, France","latlng":"43.836843, 4.359932","youtubeId":"1T8x8JkY4GA","publishedAt":"2013-01-03T15:26:43.000Z"},
{"guid":"f3ce551449ab","title":"Bouches du Rhône -  Rhone Mouth, Camargue, Provence, France","latlng":"43.496336, 4.589239","youtubeId":"Lv38xd_q-go","publishedAt":"2013-01-02T13:29:35.000Z"},
{"guid":"80e241607ab5","title":"Saintes-Maries-de-la-Mer, Provence, France","latlng":"43.451621, 4.427550","youtubeId":"iBVUBJWKXfM","publishedAt":"2012-12-31T21:23:09.000Z"},
{"guid":"49c2df1e272e","title":"Domaine du Château d'Estoublon (Mogador), Provence, France","latlng":"43.733504, 4.740683","youtubeId":"NrIgK4_GoYk","publishedAt":"2012-12-30T13:00:39.000Z"},
{"guid":"a726411b8996","title":"Seillans, French Riviera, France","latlng":"43.636376, 6.643483","youtubeId":"NTtCxJRSLu0","publishedAt":"2012-12-30T09:59:45.000Z"},
{"guid":"345d13d071c8","title":"Mougins, French Riviera, France","latlng":"43.600711, 6.995365","youtubeId":"ROtlWrCB1r4","publishedAt":"2012-12-29T18:41:12.000Z"},
{"guid":"996319d70e95","title":"Roussillon - Sentier des Ocres, Provence, France","latlng":"43.902373, 5.293064","youtubeId":"kZXMbsRVDCM","publishedAt":"2012-12-27T15:51:32.000Z"},
{"guid":"09223c9f88d5","title":"Eygalières, Provence, France","latlng":"43.760714, 4.950162","youtubeId":"q059AgwjEm4","publishedAt":"2012-12-26T11:17:07.000Z"},
{"guid":"1a33598f9ca7","title":"Oppede le Vieux, Provence, France","latlng":"43.828403, 5.161485","youtubeId":"U27rKHRMT9c","publishedAt":"2012-12-25T15:52:57.000Z"},
{"guid":"1265b07f95a1","title":"Avignon - Pont Saint-Bénezet (Pont d'Avignon), Provence, France","latlng":"43.953875, 4.804835","youtubeId":"Gy6Sc_LnF8s","publishedAt":"2012-12-24T16:42:09.000Z"},
{"guid":"81bc4ff2a9ad","title":"Avignon - Rocher des Doms Gardens, Provence, France","latlng":"43.952843, 4.807704","youtubeId":"lm5YwurP_WQ","publishedAt":"2012-12-24T10:00:00.000Z"},
{"guid":"4c54f2c68a13","title":"Avignon - Palace of the Popes, Provence, France","latlng":"43.950875, 4.807708","youtubeId":"d7hEKEpWKXU","publishedAt":"2012-12-21T11:04:33.000Z"},
{"guid":"c8f436d4be61","title":"Arles - The Amphitheatre (outside view), Provence, France","latlng":"43.677550, 4.631060","youtubeId":"oCz-76hb1LU","publishedAt":"2012-12-20T16:08:03.000Z"},
{"guid":"62c3f62a5d37","title":"Les Baux de Provence - The Castle, Provence, France","latlng":"43.744357, 4.796677","youtubeId":"gDMYruURtW4","publishedAt":"2012-12-17T18:15:58.000Z"},
{"guid":"5b5b3cbf6d34","title":"Les Baux de Provence, Provence, France","latlng":"43.743729, 4.794982","youtubeId":"xti3trWv1kg","publishedAt":"2012-12-15T13:25:44.000Z"},
{"guid":"350ebe0fd30a","title":"Saint Remy de Provence - Fête de la Transhumance, Provence, France","latlng":"43.788942, 4.831744","youtubeId":"O3tnxfvv9iM","publishedAt":"2012-12-14T17:23:12.000Z"},
{"guid":"9e951c15faa7","title":"Saint Remy de Provence - Glanum & Saint-Paul de Mausole, Provence, France","latlng":"43.773591, 4.833031","youtubeId":"Kdtby4eYjTI","publishedAt":"2012-12-13T16:58:26.000Z"},
{"guid":"657b81cf7cdd","title":"Saint Remy de Provence, Provence, France","latlng":"43.788942, 4.831744","youtubeId":"hkT7jkmo4EM","publishedAt":"2012-12-12T16:51:10.000Z"},
{"guid":"38ac8442eff3","title":"Hyeres, Provence, France","latlng":"43.120259, 6.129179","youtubeId":"V0J6_pvspKM","publishedAt":"2012-12-09T17:03:49.000Z"},
{"guid":"b0cc01abaa1e","title":"La Londe-les-Maures - Tropical Garden - Part 2 Monkeys and lemurs","latlng":"43.147645, 6.254999","youtubeId":"qFlzrShUnZU","publishedAt":"2012-12-09T16:52:25.000Z"},
{"guid":"4d59c10b0a01","title":"La Londe-les-Maures - Tropical Garden - Part 1 Birds and plants","latlng":"43.147645, 6.254999","youtubeId":"VAyx6jPONiE","publishedAt":"2012-12-08T13:36:23.000Z"},
{"guid":"c78a7c0ccc0d","title":"Tarascon - Flowers Market (Marché aux Fleurs) - Provence, France","latlng":"43.804657, 4.658537","youtubeId":"ON72zZqP40c","publishedAt":"2012-12-05T17:58:02.000Z"},
{"guid":"5db64057892a","title":"Tarascon - Country Western In Tarascon - Provence, France","latlng":"43.804657, 4.658537","youtubeId":"Z5rIOg2cdd4","publishedAt":"2012-12-03T19:06:36.000Z"},
{"guid":"7dbf67ce111c","title":"Tarascon - Cuba In Tarascon - Provence, France","latlng":"43.804657, 4.658537","youtubeId":"A2c2KhamXKI","publishedAt":"2012-12-02T17:41:08.000Z"},
{"guid":"1e977397fd4c","title":"Lunigiana & La Spezia, Tuscany & Liguria, Italy","latlng":"44.376423, 9.883232","youtubeId":"rLpGOpJf13g","publishedAt":"2012-12-02T14:28:05.000Z"},
{"guid":"be74d3870267","title":"Pont de Gau Ornithological Park - Visiting Park, Part 2 - Camargue, France","latlng":"43.487568, 4.406698","youtubeId":"RitYFOcQ0jc","publishedAt":"2012-11-29T18:56:54.000Z"},
{"guid":"6c745281d744","title":"Pont de Gau Ornithological Park - Visiting Park, Part 1 - Camargue, France","latlng":"43.487568, 4.406698","youtubeId":"RmSVz0LnK2E","publishedAt":"2012-11-29T18:56:37.000Z"},
{"guid":"2deaf1c5cd47","title":"Zakopane. Tatry. Interesująca ścieżka wiodąca do Doliny za Bramką","latlng":"49.299119, 19.948930","youtubeId":"NwWsGgxnoEM","publishedAt":"2012-11-28T19:07:29.000Z"},
{"guid":"e105469f103a","title":"Pont de Gau Ornithological Park - Big Birds - Camargue, France","latlng":"43.487568, 4.406698","youtubeId":"u2qahgaO2C4","publishedAt":"2012-11-25T16:07:05.000Z"},
{"guid":"e85a7722bc88","title":"Tourtour, Provence, Var, France","latlng":"43.588825, 6.303437","youtubeId":"AUMFQsdYCIU","publishedAt":"2012-11-16T20:25:45.000Z"},
{"guid":"5336b91288a0","title":"Sillans-la-Cascade, Provence, Var, France","latlng":"43.567372, 6.179405","youtubeId":"o60tenj3q5I","publishedAt":"2012-11-14T15:43:42.000Z"},
{"guid":"a7aaaca2a7bc","title":"Hukvaldy Castle (Zamek Hukvaldy), Historical Performance, Czech Republic","latlng":"49.620952, 18.227285","youtubeId":"rF6WrXQZs5M","publishedAt":"2012-11-12T21:23:54.000Z"},
{"guid":"aa467c392556","title":"Hukvaldy Castle (Zamek Hukvaldy, Hukvaldy Hrad, Burg Hukvaldy), Czech Republic","latlng":"49.620952, 18.227285","youtubeId":"OguhYgL0ZyA","publishedAt":"2012-11-12T19:36:42.000Z"},
{"guid":"b1212c73bc25","title":"Grasse - Fragonard Perfume Factory, French Riviera, France","latlng":"43.657255, 6.922183","youtubeId":"0t4KXDM-OyQ","publishedAt":"2012-11-10T13:37:58.000Z"},
{"guid":"0220dd8300df","title":"Grasse, French Riviera, France","latlng":"43.660514, 6.923337","youtubeId":"cUuVtJD0Ofo","publishedAt":"2012-11-10T06:25:14.000Z"},
{"guid":"96c31a07427c","title":"Pisa, Tuscany, Italy","latlng":"43.722751, 10.396236","youtubeId":"zqLWhu0Xswg","publishedAt":"2012-10-12T17:14:25.000Z"},
{"guid":"807128d8c026","title":"Štrbské Pleso, Slovakia (Slovensko, Słowacja)","latlng":"49.119873, 20.058977","youtubeId":"_JUC2lBPwX4","publishedAt":"2012-10-06T19:19:39.000Z"},
{"guid":"ff9064bcf717","title":"Oravský Podzámok, Slovakia (Slovensko)","latlng":"49.261815, 19.356511","youtubeId":"ijGUIDmfX8w","publishedAt":"2012-10-04T16:20:54.000Z"},
{"guid":"9198634a0dda","title":"Lorgues, Provence, Var, France","latlng":"43.493163, 6.361678","youtubeId":"fhCGUOWBkKo","publishedAt":"2012-09-18T05:36:48.000Z"},
{"guid":"aafdaa85d230","title":"Eze, Parc de la Grande Corniche, French Riviera, France","latlng":"43.728002, 7.361670","youtubeId":"2m3La6AtBGw","publishedAt":"2012-09-14T10:46:21.000Z"},
{"guid":"9f893cb1a5f2","title":"San Leo, Emilia-Romagna, Italy","latlng":"43.897083, 12.342642","youtubeId":"4jcFoxwSMSw","publishedAt":"2012-08-18T17:25:06.000Z"},
{"guid":"8aae586b6621","title":"Ravenna, Emilia-Romagna, Italy","latlng":"44.418042, 12.200509","youtubeId":"7_JNVGsW9XY","publishedAt":"2012-08-18T14:17:00.000Z"},
{"guid":"00819987e225","title":"Menton, French Riviera, France","latlng":"43.772626, 7.499389","youtubeId":"EhBbzpp4jM4","publishedAt":"2012-08-13T15:09:10.000Z"},
{"guid":"742270d34c9d","title":"Saint-Raphaël, French Riviera, France","latlng":"43.425603, 6.768812","youtubeId":"6KCgOd3iAsk","publishedAt":"2012-08-10T17:42:29.000Z"},
{"guid":"f880dc130687","title":"Entrecasteaux, Provence, Var, France","latlng":"43.514933, 6.243672","youtubeId":"GK4hydALN64","publishedAt":"2012-08-06T14:09:35.000Z"},
{"guid":"f48eeacfc239","title":"Fayence, French Riviera, France","latlng":"43.623942, 6.693943","youtubeId":"Et0s4hRXoBg","publishedAt":"2012-08-01T18:55:42.000Z"},
{"guid":"4b17c3512776","title":"Collobrières, French Riviera, France","latlng":"43.236968, 6.309116","youtubeId":"kjskjX-kfIk","publishedAt":"2012-07-25T19:00:25.000Z"},
{"guid":"6e701efb103c","title":"Saint-Tropez, French Riviera, France","latlng":"43.272569, 6.640547","youtubeId":"QquSSDfz5Dw","publishedAt":"2012-07-21T14:07:44.000Z"},
{"guid":"6a4e05fb5119","title":"Tourrettes-sur-Loup, French Riviera, France","latlng":"43.716022, 7.058571","youtubeId":"5mvVli1NJ2E","publishedAt":"2012-07-20T18:22:54.000Z"},
{"guid":"b063f2d9dfc4","title":"Vence, French Riviera, France","latlng":"43.722694, 7.113313","youtubeId":"r3rK_YDsyMg","publishedAt":"2012-07-19T15:16:18.000Z"},
{"guid":"010798927b04","title":"Monaco, Japanese Garden (Jardin Japonais)","latlng":"43.742397, 7.430986","youtubeId":"CBBpCRLYflA","publishedAt":"2012-07-17T17:18:08.000Z"},
{"guid":"1db149e6acff","title":"Monaco, Monte Carlo Casino","latlng":"43.739335, 7.428357","youtubeId":"4vJoNW74JYs","publishedAt":"2012-07-17T15:33:06.000Z"},
{"guid":"23e6806cc048","title":"Monaco, Opéra de Monte-Carlo","latlng":"43.738947, 7.428014","youtubeId":"eiCHLggbO1Y","publishedAt":"2012-07-15T14:33:05.000Z"},
{"guid":"7244e61e3453","title":"Monaco, Exotic Garden (Jardin Exotique)","latlng":"43.731350, 7.413946","youtubeId":"zBCj-9zfMW0","publishedAt":"2012-07-15T11:43:06.000Z"},
{"guid":"6cf9f7637c84","title":"The Oceanographic Museum of Monaco (Musée Océanographique de Monaco)","latlng":"43.730665, 7.425380","youtubeId":"S-50Qy5JsH4","publishedAt":"2012-07-14T16:26:57.000Z"},
{"guid":"dcc769c30087","title":"Monaco, Sainte-Dévote Church","latlng":"43.737511, 7.420908","youtubeId":"ScOSdnujfSI","publishedAt":"2012-07-13T16:58:26.000Z"},
{"guid":"411b5bbfb7fb","title":"Monaco-Ville (Le Rocher, Old Town), Monaco","latlng":"43.730924, 7.422579","youtubeId":"pRz-1sGiqUM","publishedAt":"2012-07-12T12:40:28.000Z"},
{"guid":"c917e47f1fe4","title":"Monaco, Prince's Palace, Changing of the Guard","latlng":"43.731405, 7.419908","youtubeId":"h6xSkZryRsc","publishedAt":"2012-07-12T10:40:37.000Z"},
{"guid":"4ad56e4c413e","title":"Abbaye Notre-Dame de Sénanque, Provence, France","latlng":"43.928305, 5.186580","youtubeId":"g7YxcOfJKrY","publishedAt":"2012-07-11T08:14:19.000Z"},
{"guid":"1afc923bfec6","title":"Roussillon, Provence, France","latlng":"43.902479, 5.292670","youtubeId":"-GskxuJb-jc","publishedAt":"2012-07-06T14:30:06.000Z"},
{"guid":"c54e619b88e2","title":"Goult, Provence, France","latlng":"43.863516, 5.242792","youtubeId":"63tpIVPVauE","publishedAt":"2012-07-05T11:47:17.000Z"},
{"guid":"b7f6755cc824","title":"Fontaine-de-Vaucluse, Provence, France","latlng":"43.921741, 5.127435","youtubeId":"jB-_ZCt4YdM","publishedAt":"2012-07-04T18:36:43.000Z"},
{"guid":"f7c171fd6cdf","title":"Gordes, Provence, France","latlng":"43.911138, 5.200431","youtubeId":"re5DJ_umI8A","publishedAt":"2012-07-04T16:16:26.000Z"},
{"guid":"e12e73b70095","title":"Èze, France, French Riviera","latlng":"43.727909, 7.361885","youtubeId":"yWIN0mAOnrA","publishedAt":"2012-07-03T15:29:53.000Z"},
{"guid":"1ddcfcb10244","title":"Beaulieu-sur-Mer and Cap Ferrat, French Riviera, France","latlng":"43.704324, 7.331539","youtubeId":"kYdvYCHPJAM","publishedAt":"2012-07-03T14:46:21.000Z"},
{"guid":"d6bdf3d53e99","title":"Frejus, French Riviera, France","latlng":"43.431926, 6.735073","youtubeId":"aBj9LAnqkUI","publishedAt":"2012-07-03T13:42:40.000Z"},
{"guid":"fed341e26137","title":"Juan-les-Pins, French Riviera, France","latlng":"43.568230, 7.110063","youtubeId":"og114J-qsbg","publishedAt":"2012-07-01T15:44:28.000Z"},
{"guid":"e1c2281a9548","title":"Cap d'Antibes, French Riviera, France","latlng":"43.544587, 7.132983","youtubeId":"yQbD8iOJZfI","publishedAt":"2012-07-01T15:37:32.000Z"},
{"guid":"dff835a14ecc","title":"Antibes, French Riviera, France","latlng":"43.580917, 7.125165","youtubeId":"B_-wyV0USU4","publishedAt":"2012-07-01T15:37:14.000Z"},
{"guid":"b26974cbe24f","title":"Cannes, French Riviera, France","latlng":"43.551327, 7.012438","youtubeId":"KrQ0DBv3cI8","publishedAt":"2012-07-01T15:36:28.000Z"},
{"guid":"f813086c6aa8","title":"A man with 4 legs in Cannes - Funny Video","latlng":"43.551327, 7.012438","youtubeId":"DWRtSIR5shk","publishedAt":"2012-07-01T15:36:14.000Z"}
]